puller/__init__.py
puller/config/__init__.py
puller-0.4.0.dist-info/LICENSE
puller-0.4.0.dist-info/METADATA
puller-0.4.0.dist-info/WHEEL
puller-0.4.0.dist-info/entry_points.txt
puller-0.4.0.dist-info/top_level.txt
puller-0.4.0.dist-info/RECORD
