Metadata-Version: 2.1
Name: puller
Version: 0.4.0
Summary: An automatic repo puller
Home-page: https://github.com/dithmer/puller
Author: Tim Dithmer
Author-email: dith.tim@gmail.com
License: UNKNOWN
Project-URL: Bug Tracker, https://github.com/dithmer/puller/issues
Platform: UNKNOWN
Classifier: Programming Language :: Python :: 3
Classifier: License :: OSI Approved :: MIT License
Classifier: Operating System :: OS Independent
Requires-Python: >=3.6
Requires-Dist: fastapi
Requires-Dist: pyyaml
Requires-Dist: uvicorn
Requires-Dist: shellescape
